AUTHORS
LICENSE
MANIFEST.in
README.rst
setup.py
dataforms/__init__.py
dataforms/app_settings.py
dataforms/fields.py
dataforms/forms.py
dataforms/models.py
dataforms/test_helpers.py
dataforms/tests.py
dataforms/urls.py
dataforms/validation_example.py
dataforms/validators.py
dataforms/views.py
dataforms/widgets.py
dataforms/admin/__init__.py
dataforms/admin/answeradmin.py
dataforms/admin/bindingadmin.py
dataforms/admin/choiceadmin.py
dataforms/admin/collectionadmin.py
dataforms/admin/dataformadmin.py
dataforms/admin/fieldadmin.py
dataforms/admin/forms.py
dataforms/admin/inlines.py
dataforms/migrations/0001_initial.py
dataforms/migrations/0002_auto__add_field_answer_type__add_field_answer_value.py
dataforms/migrations/0003_auto__del_answerchoice__del_answertext__del_answernumber__add_field_an.py
dataforms/migrations/0004_auto__del_field_answer_value__del_field_answer_choice__add_field_answe.py
dataforms/migrations/0005_auto__del_field_answer_text_value__del_field_answer_choice_value__add_.py
dataforms/migrations/0006_auto.py
dataforms/migrations/0007_auto__del_parentfield__del_binding__del_parentfieldchoice__del_childfi.py
dataforms/migrations/0008_auto__add_condition.py
dataforms/migrations/0009_auto__add_field_condition_action__add_field_condition_function.py
dataforms/migrations/0010_auto__add_answerchoice.py
dataforms/migrations/0011_auto__del_answerchoice.py
dataforms/migrations/0012_auto__del_condition__add_binding.py
dataforms/migrations/0013_auto__add_field_binding_field_choice__chg_field_binding_field.py
dataforms/migrations/0014_auto__add_field_binding_parent.py
dataforms/migrations/0015_auto__add_bindingchoice__add_bindingfield.py
dataforms/migrations/0016_auto__add_field_binding_true_field__add_field_binding_true_choice__add.py
dataforms/migrations/0017_auto__del_bindingchoice__del_bindingfield__chg_field_binding_false_fie.py
dataforms/migrations/0018_auto__del_field_binding_parent__add_field_binding_additional_rules__ch.py
django_dataforms.egg-info/PKG-INFO
django_dataforms.egg-info/SOURCES.txt
django_dataforms.egg-info/dependency_links.txt
django_dataforms.egg-info/not-zip-safe
django_dataforms.egg-info/top_level.txt
